converter/__init__.py
converter/converter.py
mcp_to_skill-2.0.0.dist-info/METADATA
mcp_to_skill-2.0.0.dist-info/WHEEL
mcp_to_skill-2.0.0.dist-info/licenses/LICENSE
mcp_to_skill-2.0.0.dist-info/RECORD
