Metadata-Version: 2.4
Name: mcp-to-skill
Version: 2.0.0
Summary: Convert MCP servers to Claude Skills with multi-transport support
Project-URL: Homepage, https://github.com/Dwsy/mcp-to-skill
Project-URL: Documentation, https://github.com/Dwsy/mcp-to-skill#readme
Project-URL: Repository, https://github.com/Dwsy/mcp-to-skill
Project-URL: Issues, https://github.com/Dwsy/mcp-to-skill/issues
Author-email: Pi Agent <pi@example.com>
License: MIT
License-File: LICENSE
Keywords: anthropic,claude,converter,mcp,model-context-protocol,skill
Classifier: Development Status :: 4 - Beta
Classifier: Intended Audience :: Developers
Classifier: License :: OSI Approved :: MIT License
Classifier: Programming Language :: Python :: 3
Classifier: Programming Language :: Python :: 3.10
Classifier: Programming Language :: Python :: 3.11
Classifier: Programming Language :: Python :: 3.12
Classifier: Topic :: Software Development :: Code Generators
Requires-Python: >=3.10
Requires-Dist: httpx>=0.25.0
Provides-Extra: dev
Requires-Dist: black>=23.0.0; extra == 'dev'
Requires-Dist: pytest-asyncio>=0.21.0; extra == 'dev'
Requires-Dist: pytest>=7.0.0; extra == 'dev'
Requires-Dist: ruff>=0.1.0; extra == 'dev'
